{"errors":[],"warnings":[],"namedChunkGroups":{"app":{"chunks":[4,3,1,0],"assets":["webpack-runtime-79d06cf44428bee1bb9e.js","webpack-runtime-79d06cf44428bee1bb9e.js.map","styles.8d6ffe7c92ebac363af8.css","styles-686674f2437428369e06.js","styles-686674f2437428369e06.js.map","commons-eaa586a5f146d51b009c.js","commons-eaa586a5f146d51b009c.js.map","app-f148a1a5c4b789e82b5f.js","app-f148a1a5c4b789e82b5f.js.map"],"children":{},"childAssets":{}},"component---src-pages-index-js":{"chunks":[2],"assets":["component---src-pages-index-js-6139e088eba9e4b6db8c.js","component---src-pages-index-js-6139e088eba9e4b6db8c.js.map"],"children":{},"childAssets":{}}},"assetsByChunkName":{"app":["webpack-runtime-79d06cf44428bee1bb9e.js","styles.8d6ffe7c92ebac363af8.css","styles-686674f2437428369e06.js","commons-eaa586a5f146d51b009c.js","app-f148a1a5c4b789e82b5f.js"],"component---src-pages-index-js":["component---src-pages-index-js-6139e088eba9e4b6db8c.js"]}}