{"errors":[],"warnings":[],"namedChunkGroups":{"app":{"chunks":[4,3,1,0],"assets":["webpack-runtime-537c20ee38cf1f6cd861.js","webpack-runtime-537c20ee38cf1f6cd861.js.map","styles.93338b8ed072dd646a73.css","styles-686674f2437428369e06.js","styles-686674f2437428369e06.js.map","commons-eaa586a5f146d51b009c.js","commons-eaa586a5f146d51b009c.js.map","app-f148a1a5c4b789e82b5f.js","app-f148a1a5c4b789e82b5f.js.map"],"children":{},"childAssets":{}},"component---src-pages-index-js":{"chunks":[2],"assets":["component---src-pages-index-js-8b96cdf93bb227ed9f48.js","component---src-pages-index-js-8b96cdf93bb227ed9f48.js.map"],"children":{},"childAssets":{}}},"assetsByChunkName":{"app":["webpack-runtime-537c20ee38cf1f6cd861.js","styles.93338b8ed072dd646a73.css","styles-686674f2437428369e06.js","commons-eaa586a5f146d51b009c.js","app-f148a1a5c4b789e82b5f.js"],"component---src-pages-index-js":["component---src-pages-index-js-8b96cdf93bb227ed9f48.js"]}}